jsonref.py
proxytypes.py
jsonref-1.0.0.post1.dist-info/LICENSE
jsonref-1.0.0.post1.dist-info/WHEEL
jsonref-1.0.0.post1.dist-info/METADATA
jsonref-1.0.0.post1.dist-info/RECORD
