Metadata-Version: 2.1
Name: jsonref
Version: 1.0.0.post1
Summary: jsonref is a library for automatic dereferencing of JSON Reference objects for Python.
Home-page: https://github.com/gazpachoking/jsonref
License: MIT
Author: Chase Sterling
Author-email: chase.sterling@gmail.com
Requires-Python: >=3.3,<4.0
Classifier: License :: OSI Approved :: MIT License
Classifier: Programming Language :: Python :: 3
Classifier: Programming Language :: Python :: 3.4
Classifier: Programming Language :: Python :: 3.5
Classifier: Programming Language :: Python :: 3.6
Classifier: Programming Language :: Python :: 3.7
Classifier: Programming Language :: Python :: 3.8
Classifier: Programming Language :: Python :: 3.9
Classifier: Programming Language :: Python :: 3.10
Classifier: Programming Language :: Python :: 3.11
Project-URL: Documentation, https://jsonref.readthedocs.io/en/latest/
Project-URL: Repository, https://github.com/gazpachoking/jsonref
